capatsv/__init__.py
capatsv/capatsv.py
capatsv-0.0.2.dist-info/METADATA
capatsv-0.0.2.dist-info/WHEEL
capatsv-0.0.2.dist-info/entry_points.txt
capatsv-0.0.2.dist-info/top_level.txt
capatsv-0.0.2.dist-info/RECORD
